{
  "login": "adrianjagielak",
  "name": null,
  "avatarUrl": "https://avatars.githubusercontent.com/u/21083675?v=4",
  "htmlUrl": "https://github.com/adrianjagielak",
  "location": null,
  "countryCode": null,
  "generatedAt": "2026-07-08T11:58:46.468Z",
  "isPartial": true,
  "languages": [
    {
      "language": {
        "slug": "typescript",
        "name": "TypeScript",
        "githubQuery": "TypeScript"
      },
      "starsPrimary": 302,
      "repoCountPrimary": 1,
      "starsContains": 302,
      "repoCountContains": 1,
      "globalRank": null,
      "countryRank": null,
      "topRepos": [
        {
          "name": "home-assistant-futurehome",
          "fullName": "adrianjagielak/home-assistant-futurehome",
          "stars": 302,
          "url": "https://github.com/adrianjagielak/home-assistant-futurehome",
          "primaryLanguage": "TypeScript"
        }
      ]
    }
  ]
}
