{
  "login": "alan2207",
  "name": null,
  "avatarUrl": "https://avatars.githubusercontent.com/u/12713315?v=4",
  "htmlUrl": "https://github.com/alan2207",
  "location": null,
  "countryCode": null,
  "generatedAt": "2026-05-31T13:50:40.799Z",
  "isPartial": true,
  "languages": [
    {
      "language": {
        "slug": "typescript",
        "name": "TypeScript",
        "githubQuery": "TypeScript"
      },
      "starsPrimary": 35212,
      "repoCountPrimary": 1,
      "starsContains": 35212,
      "repoCountContains": 1,
      "globalRank": 25,
      "countryRank": null,
      "topRepos": [
        {
          "name": "bulletproof-react",
          "fullName": "alan2207/bulletproof-react",
          "stars": 35212,
          "url": "https://github.com/alan2207/bulletproof-react",
          "primaryLanguage": "TypeScript"
        }
      ]
    }
  ]
}
