{
  "login": "Anmours",
  "name": null,
  "avatarUrl": "https://avatars.githubusercontent.com/u/76721799?v=4",
  "htmlUrl": "https://github.com/Anmours",
  "location": null,
  "countryCode": null,
  "generatedAt": "2026-06-01T11:12:57.386Z",
  "isPartial": true,
  "languages": [
    {
      "language": {
        "slug": "typescript",
        "name": "TypeScript",
        "githubQuery": "TypeScript"
      },
      "starsPrimary": 381,
      "repoCountPrimary": 1,
      "starsContains": 381,
      "repoCountContains": 1,
      "globalRank": null,
      "countryRank": null,
      "topRepos": [
        {
          "name": "Bncr",
          "fullName": "Anmours/Bncr",
          "stars": 381,
          "url": "https://github.com/Anmours/Bncr",
          "primaryLanguage": "TypeScript"
        }
      ]
    }
  ]
}
