{
  "login": "babarot",
  "name": null,
  "avatarUrl": "https://avatars.githubusercontent.com/u/4442708?v=4",
  "htmlUrl": "https://github.com/babarot",
  "location": null,
  "countryCode": null,
  "generatedAt": "2026-06-21T12:22:04.497Z",
  "isPartial": true,
  "languages": [
    {
      "language": {
        "slug": "typescript",
        "name": "TypeScript",
        "githubQuery": "TypeScript"
      },
      "starsPrimary": 413,
      "repoCountPrimary": 1,
      "starsContains": 413,
      "repoCountContains": 1,
      "globalRank": null,
      "countryRank": null,
      "topRepos": [
        {
          "name": "oksskolten",
          "fullName": "babarot/oksskolten",
          "stars": 413,
          "url": "https://github.com/babarot/oksskolten",
          "primaryLanguage": "TypeScript"
        }
      ]
    }
  ]
}
