{
  "login": "chenyme",
  "name": null,
  "avatarUrl": "https://avatars.githubusercontent.com/u/118253778?v=4",
  "htmlUrl": "https://github.com/chenyme",
  "location": null,
  "countryCode": null,
  "generatedAt": "2026-07-06T23:32:47.591Z",
  "isPartial": true,
  "languages": [
    {
      "language": {
        "slug": "typescript",
        "name": "TypeScript",
        "githubQuery": "TypeScript"
      },
      "starsPrimary": 103,
      "repoCountPrimary": 1,
      "starsContains": 103,
      "repoCountContains": 1,
      "globalRank": null,
      "countryRank": null,
      "topRepos": [
        {
          "name": "LINUX-DO-WIKI",
          "fullName": "chenyme/LINUX-DO-WIKI",
          "stars": 103,
          "url": "https://github.com/chenyme/LINUX-DO-WIKI",
          "primaryLanguage": "TypeScript"
        }
      ]
    }
  ]
}
