{
  "login": "cx8537",
  "name": null,
  "avatarUrl": "https://avatars.githubusercontent.com/u/10858983?v=4",
  "htmlUrl": "https://github.com/cx8537",
  "location": null,
  "countryCode": null,
  "generatedAt": "2026-05-31T23:16:10.146Z",
  "isPartial": true,
  "languages": [
    {
      "language": {
        "slug": "typescript",
        "name": "TypeScript",
        "githubQuery": "TypeScript"
      },
      "starsPrimary": 113,
      "repoCountPrimary": 1,
      "starsContains": 113,
      "repoCountContains": 1,
      "globalRank": null,
      "countryRank": null,
      "topRepos": [
        {
          "name": "sidabari",
          "fullName": "cx8537/sidabari",
          "stars": 113,
          "url": "https://github.com/cx8537/sidabari",
          "primaryLanguage": "TypeScript"
        }
      ]
    }
  ]
}
