{
  "login": "darshanpawar101",
  "name": null,
  "avatarUrl": "https://avatars.githubusercontent.com/u/46950192?v=4",
  "htmlUrl": "https://github.com/darshanpawar101",
  "location": null,
  "countryCode": null,
  "generatedAt": "2026-06-13T23:34:42.905Z",
  "isPartial": true,
  "languages": [
    {
      "language": {
        "slug": "typescript",
        "name": "TypeScript",
        "githubQuery": "TypeScript"
      },
      "starsPrimary": 351,
      "repoCountPrimary": 1,
      "starsContains": 351,
      "repoCountContains": 1,
      "globalRank": null,
      "countryRank": null,
      "topRepos": [
        {
          "name": "Coffee-Shop-App",
          "fullName": "darshanpawar101/Coffee-Shop-App",
          "stars": 351,
          "url": "https://github.com/darshanpawar101/Coffee-Shop-App",
          "primaryLanguage": "TypeScript"
        }
      ]
    }
  ]
}
