{
  "login": "Desdaemon",
  "name": null,
  "avatarUrl": "https://avatars.githubusercontent.com/u/36768030?v=4",
  "htmlUrl": "https://github.com/Desdaemon",
  "location": null,
  "countryCode": null,
  "generatedAt": "2026-06-03T00:03:59.503Z",
  "isPartial": true,
  "languages": [
    {
      "language": {
        "slug": "typescript",
        "name": "TypeScript",
        "githubQuery": "TypeScript"
      },
      "starsPrimary": 167,
      "repoCountPrimary": 1,
      "starsContains": 167,
      "repoCountContains": 1,
      "globalRank": null,
      "countryRank": null,
      "topRepos": [
        {
          "name": "typed-htmx",
          "fullName": "Desdaemon/typed-htmx",
          "stars": 167,
          "url": "https://github.com/Desdaemon/typed-htmx",
          "primaryLanguage": "TypeScript"
        }
      ]
    }
  ]
}
