{
  "login": "dsifford",
  "name": null,
  "avatarUrl": "https://avatars.githubusercontent.com/u/5240018?v=4",
  "htmlUrl": "https://github.com/dsifford",
  "location": null,
  "countryCode": null,
  "generatedAt": "2026-06-27T11:47:40.669Z",
  "isPartial": true,
  "languages": [
    {
      "language": {
        "slug": "typescript",
        "name": "TypeScript",
        "githubQuery": "TypeScript"
      },
      "starsPrimary": 126,
      "repoCountPrimary": 1,
      "starsContains": 126,
      "repoCountContains": 1,
      "globalRank": null,
      "countryRank": null,
      "topRepos": [
        {
          "name": "academic-bloggers-toolkit",
          "fullName": "dsifford/academic-bloggers-toolkit",
          "stars": 126,
          "url": "https://github.com/dsifford/academic-bloggers-toolkit",
          "primaryLanguage": "TypeScript"
        }
      ]
    }
  ]
}
