{
  "login": "dualface",
  "name": null,
  "avatarUrl": "https://avatars.githubusercontent.com/u/62318?v=4",
  "htmlUrl": "https://github.com/dualface",
  "location": null,
  "countryCode": null,
  "generatedAt": "2026-07-17T23:10:56.767Z",
  "isPartial": true,
  "languages": [
    {
      "language": {
        "slug": "typescript",
        "name": "TypeScript",
        "githubQuery": "TypeScript"
      },
      "starsPrimary": 115,
      "repoCountPrimary": 1,
      "starsContains": 115,
      "repoCountContains": 1,
      "globalRank": null,
      "countryRank": null,
      "topRepos": [
        {
          "name": "iam-ecs-typescript",
          "fullName": "dualface/iam-ecs-typescript",
          "stars": 115,
          "url": "https://github.com/dualface/iam-ecs-typescript",
          "primaryLanguage": "TypeScript"
        }
      ]
    }
  ]
}
