{
  "login": "elsbrock",
  "name": null,
  "avatarUrl": "https://avatars.githubusercontent.com/u/77769?v=4",
  "htmlUrl": "https://github.com/elsbrock",
  "location": null,
  "countryCode": null,
  "generatedAt": "2026-06-13T23:34:42.905Z",
  "isPartial": true,
  "languages": [
    {
      "language": {
        "slug": "typescript",
        "name": "TypeScript",
        "githubQuery": "TypeScript"
      },
      "starsPrimary": 326,
      "repoCountPrimary": 1,
      "starsContains": 326,
      "repoCountContains": 1,
      "globalRank": null,
      "countryRank": null,
      "topRepos": [
        {
          "name": "hetzner-radar",
          "fullName": "elsbrock/hetzner-radar",
          "stars": 326,
          "url": "https://github.com/elsbrock/hetzner-radar",
          "primaryLanguage": "TypeScript"
        }
      ]
    }
  ]
}
