{
  "login": "fczbkk",
  "name": null,
  "avatarUrl": "https://avatars.githubusercontent.com/u/43734?v=4",
  "htmlUrl": "https://github.com/fczbkk",
  "location": null,
  "countryCode": null,
  "generatedAt": "2026-07-20T12:26:44.279Z",
  "isPartial": true,
  "languages": [
    {
      "language": {
        "slug": "typescript",
        "name": "TypeScript",
        "githubQuery": "TypeScript"
      },
      "starsPrimary": 782,
      "repoCountPrimary": 2,
      "starsContains": 782,
      "repoCountContains": 2,
      "globalRank": null,
      "countryRank": null,
      "topRepos": [
        {
          "name": "css-selector-generator",
          "fullName": "fczbkk/css-selector-generator",
          "stars": 594,
          "url": "https://github.com/fczbkk/css-selector-generator",
          "primaryLanguage": "TypeScript"
        },
        {
          "name": "css-selector-generator-benchmark",
          "fullName": "fczbkk/css-selector-generator-benchmark",
          "stars": 188,
          "url": "https://github.com/fczbkk/css-selector-generator-benchmark",
          "primaryLanguage": "TypeScript"
        }
      ]
    }
  ]
}
