{
  "login": "fergarrui",
  "name": null,
  "avatarUrl": "https://avatars.githubusercontent.com/u/4693676?v=4",
  "htmlUrl": "https://github.com/fergarrui",
  "location": null,
  "countryCode": null,
  "generatedAt": "2026-07-24T11:57:07.515Z",
  "isPartial": true,
  "languages": [
    {
      "language": {
        "slug": "typescript",
        "name": "TypeScript",
        "githubQuery": "TypeScript"
      },
      "starsPrimary": 352,
      "repoCountPrimary": 1,
      "starsContains": 352,
      "repoCountContains": 1,
      "globalRank": null,
      "countryRank": null,
      "topRepos": [
        {
          "name": "ethereum-graph-debugger",
          "fullName": "fergarrui/ethereum-graph-debugger",
          "stars": 352,
          "url": "https://github.com/fergarrui/ethereum-graph-debugger",
          "primaryLanguage": "TypeScript"
        }
      ]
    }
  ]
}
