{
  "login": "finedaybreak",
  "name": null,
  "avatarUrl": "https://avatars.githubusercontent.com/u/94026641?v=4",
  "htmlUrl": "https://github.com/finedaybreak",
  "location": null,
  "countryCode": null,
  "generatedAt": "2026-05-31T21:54:15.042Z",
  "isPartial": true,
  "languages": [
    {
      "language": {
        "slug": "typescript",
        "name": "TypeScript",
        "githubQuery": "TypeScript"
      },
      "starsPrimary": 328,
      "repoCountPrimary": 1,
      "starsContains": 328,
      "repoCountContains": 1,
      "globalRank": null,
      "countryRank": null,
      "topRepos": [
        {
          "name": "keepalive-for-react",
          "fullName": "finedaybreak/keepalive-for-react",
          "stars": 328,
          "url": "https://github.com/finedaybreak/keepalive-for-react",
          "primaryLanguage": "TypeScript"
        }
      ]
    }
  ]
}
