{
  "login": "haythem",
  "name": null,
  "avatarUrl": "https://avatars.githubusercontent.com/u/1000991?v=4",
  "htmlUrl": "https://github.com/haythem",
  "location": null,
  "countryCode": null,
  "generatedAt": "2026-07-03T23:29:30.490Z",
  "isPartial": true,
  "languages": [
    {
      "language": {
        "slug": "typescript",
        "name": "TypeScript",
        "githubQuery": "TypeScript"
      },
      "starsPrimary": 125,
      "repoCountPrimary": 1,
      "starsContains": 125,
      "repoCountContains": 1,
      "globalRank": null,
      "countryRank": null,
      "topRepos": [
        {
          "name": "public-ip",
          "fullName": "haythem/public-ip",
          "stars": 125,
          "url": "https://github.com/haythem/public-ip",
          "primaryLanguage": "TypeScript"
        }
      ]
    }
  ]
}
