{
  "login": "Higurashi-kagome",
  "name": null,
  "avatarUrl": "https://avatars.githubusercontent.com/u/51501079?v=4",
  "htmlUrl": "https://github.com/Higurashi-kagome",
  "location": null,
  "countryCode": null,
  "generatedAt": "2026-07-17T11:43:08.461Z",
  "isPartial": true,
  "languages": [
    {
      "language": {
        "slug": "typescript",
        "name": "TypeScript",
        "githubQuery": "TypeScript"
      },
      "starsPrimary": 778,
      "repoCountPrimary": 1,
      "starsContains": 778,
      "repoCountContains": 1,
      "globalRank": null,
      "countryRank": null,
      "topRepos": [
        {
          "name": "wereader",
          "fullName": "Higurashi-kagome/wereader",
          "stars": 778,
          "url": "https://github.com/Higurashi-kagome/wereader",
          "primaryLanguage": "TypeScript"
        }
      ]
    }
  ]
}
