{
  "login": "howardchung",
  "name": null,
  "avatarUrl": "https://avatars.githubusercontent.com/u/3134520?v=4",
  "htmlUrl": "https://github.com/howardchung",
  "location": null,
  "countryCode": null,
  "generatedAt": "2026-07-24T11:57:07.515Z",
  "isPartial": true,
  "languages": [
    {
      "language": {
        "slug": "typescript",
        "name": "TypeScript",
        "githubQuery": "TypeScript"
      },
      "starsPrimary": 1139,
      "repoCountPrimary": 1,
      "starsContains": 1139,
      "repoCountContains": 1,
      "globalRank": null,
      "countryRank": null,
      "topRepos": [
        {
          "name": "watchparty",
          "fullName": "howardchung/watchparty",
          "stars": 1139,
          "url": "https://github.com/howardchung/watchparty",
          "primaryLanguage": "TypeScript"
        }
      ]
    }
  ]
}
