{
  "login": "JedWatson",
  "name": "Jed Watson",
  "avatarUrl": "https://avatars.githubusercontent.com/u/872310?v=4",
  "htmlUrl": "https://github.com/JedWatson",
  "location": "Sydney",
  "countryCode": null,
  "generatedAt": "2026-06-09T23:44:57.230Z",
  "isPartial": true,
  "languages": [
    {
      "language": {
        "slug": "typescript",
        "name": "TypeScript",
        "githubQuery": "TypeScript"
      },
      "starsPrimary": 28046,
      "repoCountPrimary": 1,
      "starsContains": 28046,
      "repoCountContains": 1,
      "globalRank": 50,
      "countryRank": null,
      "topRepos": [
        {
          "name": "react-select",
          "fullName": "JedWatson/react-select",
          "stars": 28046,
          "url": "https://github.com/JedWatson/react-select",
          "primaryLanguage": "TypeScript"
        }
      ]
    }
  ]
}
