{
  "login": "jnsahaj",
  "name": "Sahaj Jain",
  "avatarUrl": "https://avatars.githubusercontent.com/u/82111591?v=4",
  "htmlUrl": "https://github.com/jnsahaj",
  "location": null,
  "countryCode": null,
  "generatedAt": "2026-06-08T14:31:45.946Z",
  "isPartial": true,
  "languages": [
    {
      "language": {
        "slug": "typescript",
        "name": "TypeScript",
        "githubQuery": "TypeScript"
      },
      "starsPrimary": 9935,
      "repoCountPrimary": 1,
      "starsContains": 9935,
      "repoCountContains": 1,
      "globalRank": 223,
      "countryRank": null,
      "topRepos": [
        {
          "name": "tweakcn",
          "fullName": "jnsahaj/tweakcn",
          "stars": 9935,
          "url": "https://github.com/jnsahaj/tweakcn",
          "primaryLanguage": "TypeScript"
        }
      ]
    }
  ]
}
