{
  "login": "joway",
  "name": null,
  "avatarUrl": "https://avatars.githubusercontent.com/u/8353464?v=4",
  "htmlUrl": "https://github.com/joway",
  "location": null,
  "countryCode": null,
  "generatedAt": "2026-06-14T12:17:31.442Z",
  "isPartial": true,
  "languages": [
    {
      "language": {
        "slug": "typescript",
        "name": "TypeScript",
        "githubQuery": "TypeScript"
      },
      "starsPrimary": 196,
      "repoCountPrimary": 1,
      "starsContains": 196,
      "repoCountContains": 1,
      "globalRank": null,
      "countryRank": null,
      "topRepos": [
        {
          "name": "sheetsql",
          "fullName": "joway/sheetsql",
          "stars": 196,
          "url": "https://github.com/joway/sheetsql",
          "primaryLanguage": "TypeScript"
        }
      ]
    }
  ]
}
