{
  "login": "kikootwo",
  "name": null,
  "avatarUrl": "https://avatars.githubusercontent.com/u/14036771?v=4",
  "htmlUrl": "https://github.com/kikootwo",
  "location": null,
  "countryCode": null,
  "generatedAt": "2026-06-16T15:23:30.344Z",
  "isPartial": true,
  "languages": [
    {
      "language": {
        "slug": "typescript",
        "name": "TypeScript",
        "githubQuery": "TypeScript"
      },
      "starsPrimary": 703,
      "repoCountPrimary": 1,
      "starsContains": 703,
      "repoCountContains": 1,
      "globalRank": null,
      "countryRank": null,
      "topRepos": [
        {
          "name": "ReadMeABook",
          "fullName": "kikootwo/ReadMeABook",
          "stars": 703,
          "url": "https://github.com/kikootwo/ReadMeABook",
          "primaryLanguage": "TypeScript"
        }
      ]
    }
  ]
}
