{
  "login": "kitschpatrol",
  "name": null,
  "avatarUrl": "https://avatars.githubusercontent.com/u/194164?v=4",
  "htmlUrl": "https://github.com/kitschpatrol",
  "location": null,
  "countryCode": null,
  "generatedAt": "2026-06-11T14:13:15.086Z",
  "isPartial": true,
  "languages": [
    {
      "language": {
        "slug": "typescript",
        "name": "TypeScript",
        "githubQuery": "TypeScript"
      },
      "starsPrimary": 165,
      "repoCountPrimary": 1,
      "starsContains": 165,
      "repoCountContains": 1,
      "globalRank": null,
      "countryRank": null,
      "topRepos": [
        {
          "name": "yanki-obsidian",
          "fullName": "kitschpatrol/yanki-obsidian",
          "stars": 165,
          "url": "https://github.com/kitschpatrol/yanki-obsidian",
          "primaryLanguage": "TypeScript"
        }
      ]
    }
  ]
}
