{
  "login": "kristoferlund",
  "name": null,
  "avatarUrl": "https://avatars.githubusercontent.com/u/9698363?v=4",
  "htmlUrl": "https://github.com/kristoferlund",
  "location": null,
  "countryCode": null,
  "generatedAt": "2026-06-06T11:47:43.958Z",
  "isPartial": true,
  "languages": [
    {
      "language": {
        "slug": "typescript",
        "name": "TypeScript",
        "githubQuery": "TypeScript"
      },
      "starsPrimary": 167,
      "repoCountPrimary": 1,
      "starsContains": 167,
      "repoCountContains": 1,
      "globalRank": null,
      "countryRank": null,
      "topRepos": [
        {
          "name": "duet-gpt",
          "fullName": "kristoferlund/duet-gpt",
          "stars": 167,
          "url": "https://github.com/kristoferlund/duet-gpt",
          "primaryLanguage": "TypeScript"
        }
      ]
    }
  ]
}
