{
  "login": "mellow-fox",
  "name": null,
  "avatarUrl": "https://avatars.githubusercontent.com/u/205186802?v=4",
  "htmlUrl": "https://github.com/mellow-fox",
  "location": null,
  "countryCode": null,
  "generatedAt": "2026-07-17T11:43:08.461Z",
  "isPartial": true,
  "languages": [
    {
      "language": {
        "slug": "typescript",
        "name": "TypeScript",
        "githubQuery": "TypeScript"
      },
      "starsPrimary": 107,
      "repoCountPrimary": 1,
      "starsContains": 107,
      "repoCountContains": 1,
      "globalRank": null,
      "countryRank": null,
      "topRepos": [
        {
          "name": "TidyQuest",
          "fullName": "mellow-fox/TidyQuest",
          "stars": 107,
          "url": "https://github.com/mellow-fox/TidyQuest",
          "primaryLanguage": "TypeScript"
        }
      ]
    }
  ]
}
