{
  "login": "Mif2006",
  "name": null,
  "avatarUrl": "https://avatars.githubusercontent.com/u/114983743?v=4",
  "htmlUrl": "https://github.com/Mif2006",
  "location": null,
  "countryCode": null,
  "generatedAt": "2026-07-15T23:14:34.688Z",
  "isPartial": true,
  "languages": [
    {
      "language": {
        "slug": "typescript",
        "name": "TypeScript",
        "githubQuery": "TypeScript"
      },
      "starsPrimary": 320,
      "repoCountPrimary": 1,
      "starsContains": 320,
      "repoCountContains": 1,
      "globalRank": null,
      "countryRank": null,
      "topRepos": [
        {
          "name": "Space-Portolio",
          "fullName": "Mif2006/Space-Portolio",
          "stars": 320,
          "url": "https://github.com/Mif2006/Space-Portolio",
          "primaryLanguage": "TypeScript"
        }
      ]
    }
  ]
}
