{
  "login": "MurhafSousli",
  "name": "Murhaf Sousli",
  "avatarUrl": "https://avatars.githubusercontent.com/u/8130692?v=4",
  "htmlUrl": "https://github.com/MurhafSousli",
  "location": "Mainz, Germany",
  "countryCode": null,
  "generatedAt": "2026-06-16T15:23:30.344Z",
  "isPartial": true,
  "languages": [
    {
      "language": {
        "slug": "typescript",
        "name": "TypeScript",
        "githubQuery": "TypeScript"
      },
      "starsPrimary": 3608,
      "repoCountPrimary": 8,
      "starsContains": 3608,
      "repoCountContains": 8,
      "globalRank": 738,
      "countryRank": null,
      "topRepos": [
        {
          "name": "ngx-progressbar",
          "fullName": "MurhafSousli/ngx-progressbar",
          "stars": 1054,
          "url": "https://github.com/MurhafSousli/ngx-progressbar",
          "primaryLanguage": "TypeScript"
        },
        {
          "name": "ngx-scrollbar",
          "fullName": "MurhafSousli/ngx-scrollbar",
          "stars": 655,
          "url": "https://github.com/MurhafSousli/ngx-scrollbar",
          "primaryLanguage": "TypeScript"
        },
        {
          "name": "ngx-gallery",
          "fullName": "MurhafSousli/ngx-gallery",
          "stars": 636,
          "url": "https://github.com/MurhafSousli/ngx-gallery",
          "primaryLanguage": "TypeScript"
        },
        {
          "name": "ngx-sharebuttons",
          "fullName": "MurhafSousli/ngx-sharebuttons",
          "stars": 535,
          "url": "https://github.com/MurhafSousli/ngx-sharebuttons",
          "primaryLanguage": "TypeScript"
        },
        {
          "name": "ngx-highlightjs",
          "fullName": "MurhafSousli/ngx-highlightjs",
          "stars": 293,
          "url": "https://github.com/MurhafSousli/ngx-highlightjs",
          "primaryLanguage": "TypeScript"
        }
      ]
    }
  ]
}
