{
  "login": "newdee",
  "name": null,
  "avatarUrl": "https://avatars.githubusercontent.com/u/12610440?v=4",
  "htmlUrl": "https://github.com/newdee",
  "location": null,
  "countryCode": null,
  "generatedAt": "2026-07-24T11:57:07.515Z",
  "isPartial": true,
  "languages": [
    {
      "language": {
        "slug": "typescript",
        "name": "TypeScript",
        "githubQuery": "TypeScript"
      },
      "starsPrimary": 178,
      "repoCountPrimary": 1,
      "starsContains": 178,
      "repoCountContains": 1,
      "globalRank": null,
      "countryRank": null,
      "topRepos": [
        {
          "name": "prompt-shelf",
          "fullName": "newdee/prompt-shelf",
          "stars": 178,
          "url": "https://github.com/newdee/prompt-shelf",
          "primaryLanguage": "TypeScript"
        }
      ]
    }
  ]
}
