{
  "login": "NiclasDev63",
  "name": null,
  "avatarUrl": "https://avatars.githubusercontent.com/u/83044113?v=4",
  "htmlUrl": "https://github.com/NiclasDev63",
  "location": null,
  "countryCode": null,
  "generatedAt": "2026-06-13T12:04:16.683Z",
  "isPartial": true,
  "languages": [
    {
      "language": {
        "slug": "typescript",
        "name": "TypeScript",
        "githubQuery": "TypeScript"
      },
      "starsPrimary": 153,
      "repoCountPrimary": 1,
      "starsContains": 153,
      "repoCountContains": 1,
      "globalRank": null,
      "countryRank": null,
      "topRepos": [
        {
          "name": "tiptap-extension-global-drag-handle",
          "fullName": "NiclasDev63/tiptap-extension-global-drag-handle",
          "stars": 153,
          "url": "https://github.com/NiclasDev63/tiptap-extension-global-drag-handle",
          "primaryLanguage": "TypeScript"
        }
      ]
    }
  ]
}
