{
  "login": "Rayzeq",
  "name": null,
  "avatarUrl": "https://avatars.githubusercontent.com/u/26172375?v=4",
  "htmlUrl": "https://github.com/Rayzeq",
  "location": null,
  "countryCode": null,
  "generatedAt": "2026-06-27T11:47:40.669Z",
  "isPartial": true,
  "languages": [
    {
      "language": {
        "slug": "typescript",
        "name": "TypeScript",
        "githubQuery": "TypeScript"
      },
      "starsPrimary": 148,
      "repoCountPrimary": 1,
      "starsContains": 148,
      "repoCountContains": 1,
      "globalRank": null,
      "countryRank": null,
      "topRepos": [
        {
          "name": "quick-settings-audio-panel",
          "fullName": "Rayzeq/quick-settings-audio-panel",
          "stars": 148,
          "url": "https://github.com/Rayzeq/quick-settings-audio-panel",
          "primaryLanguage": "TypeScript"
        }
      ]
    }
  ]
}
