{
  "login": "suyash",
  "name": null,
  "avatarUrl": "https://avatars.githubusercontent.com/u/16324837?v=4",
  "htmlUrl": "https://github.com/suyash",
  "location": null,
  "countryCode": null,
  "generatedAt": "2026-07-10T12:38:07.554Z",
  "isPartial": true,
  "languages": [
    {
      "language": {
        "slug": "typescript",
        "name": "TypeScript",
        "githubQuery": "TypeScript"
      },
      "starsPrimary": 172,
      "repoCountPrimary": 1,
      "starsContains": 172,
      "repoCountContains": 1,
      "globalRank": null,
      "countryRank": null,
      "topRepos": [
        {
          "name": "flowy",
          "fullName": "suyash/flowy",
          "stars": 172,
          "url": "https://github.com/suyash/flowy",
          "primaryLanguage": "TypeScript"
        }
      ]
    }
  ]
}
