{
  "login": "teles",
  "name": null,
  "avatarUrl": "https://avatars.githubusercontent.com/u/762639?v=4",
  "htmlUrl": "https://github.com/teles",
  "location": null,
  "countryCode": null,
  "generatedAt": "2026-06-24T23:35:54.043Z",
  "isPartial": true,
  "languages": [
    {
      "language": {
        "slug": "typescript",
        "name": "TypeScript",
        "githubQuery": "TypeScript"
      },
      "starsPrimary": 852,
      "repoCountPrimary": 1,
      "starsContains": 852,
      "repoCountContains": 1,
      "globalRank": null,
      "countryRank": null,
      "topRepos": [
        {
          "name": "awesome-seo",
          "fullName": "teles/awesome-seo",
          "stars": 852,
          "url": "https://github.com/teles/awesome-seo",
          "primaryLanguage": "TypeScript"
        }
      ]
    }
  ]
}
