{
  "login": "tom-james-watson",
  "name": "Tom Watson",
  "avatarUrl": "https://avatars.githubusercontent.com/u/3852719?v=4",
  "htmlUrl": "https://github.com/tom-james-watson",
  "location": "Madrid, Spain",
  "countryCode": null,
  "generatedAt": "2026-07-23T23:13:51.073Z",
  "isPartial": true,
  "languages": [
    {
      "language": {
        "slug": "typescript",
        "name": "TypeScript",
        "githubQuery": "TypeScript"
      },
      "starsPrimary": 2749,
      "repoCountPrimary": 3,
      "starsContains": 2749,
      "repoCountContains": 3,
      "globalRank": 977,
      "countryRank": null,
      "topRepos": [
        {
          "name": "breaktimer-app",
          "fullName": "tom-james-watson/breaktimer-app",
          "stars": 1508,
          "url": "https://github.com/tom-james-watson/breaktimer-app",
          "primaryLanguage": "TypeScript"
        },
        {
          "name": "p2p.chat",
          "fullName": "tom-james-watson/p2p.chat",
          "stars": 678,
          "url": "https://github.com/tom-james-watson/p2p.chat",
          "primaryLanguage": "TypeScript"
        },
        {
          "name": "wikitrivia",
          "fullName": "tom-james-watson/wikitrivia",
          "stars": 563,
          "url": "https://github.com/tom-james-watson/wikitrivia",
          "primaryLanguage": "TypeScript"
        }
      ]
    }
  ]
}
