{
  "login": "tony1223",
  "name": null,
  "avatarUrl": "https://avatars.githubusercontent.com/u/225971?v=4",
  "htmlUrl": "https://github.com/tony1223",
  "location": null,
  "countryCode": null,
  "generatedAt": "2026-06-07T23:31:46.049Z",
  "isPartial": true,
  "languages": [
    {
      "language": {
        "slug": "typescript",
        "name": "TypeScript",
        "githubQuery": "TypeScript"
      },
      "starsPrimary": 398,
      "repoCountPrimary": 1,
      "starsContains": 398,
      "repoCountContains": 1,
      "globalRank": null,
      "countryRank": null,
      "topRepos": [
        {
          "name": "better-agent-terminal",
          "fullName": "tony1223/better-agent-terminal",
          "stars": 398,
          "url": "https://github.com/tony1223/better-agent-terminal",
          "primaryLanguage": "TypeScript"
        }
      ]
    }
  ]
}
