{
  "login": "TornadoInsight",
  "name": null,
  "avatarUrl": "https://avatars.githubusercontent.com/u/53037786?v=4",
  "htmlUrl": "https://github.com/TornadoInsight",
  "location": null,
  "countryCode": null,
  "generatedAt": "2026-07-06T23:32:47.591Z",
  "isPartial": true,
  "languages": [
    {
      "language": {
        "slug": "typescript",
        "name": "TypeScript",
        "githubQuery": "TypeScript"
      },
      "starsPrimary": 111,
      "repoCountPrimary": 1,
      "starsContains": 111,
      "repoCountContains": 1,
      "globalRank": null,
      "countryRank": null,
      "topRepos": [
        {
          "name": "Sora-FullStack",
          "fullName": "TornadoInsight/Sora-FullStack",
          "stars": 111,
          "url": "https://github.com/TornadoInsight/Sora-FullStack",
          "primaryLanguage": "TypeScript"
        }
      ]
    }
  ]
}
