{
  "login": "Vaccarini-Lorenzo",
  "name": null,
  "avatarUrl": "https://avatars.githubusercontent.com/u/80112134?v=4",
  "htmlUrl": "https://github.com/Vaccarini-Lorenzo",
  "location": null,
  "countryCode": null,
  "generatedAt": "2026-07-22T23:17:19.565Z",
  "isPartial": true,
  "languages": [
    {
      "language": {
        "slug": "typescript",
        "name": "TypeScript",
        "githubQuery": "TypeScript"
      },
      "starsPrimary": 106,
      "repoCountPrimary": 1,
      "starsContains": 106,
      "repoCountContains": 1,
      "globalRank": null,
      "countryRank": null,
      "topRepos": [
        {
          "name": "MagicCalendar",
          "fullName": "Vaccarini-Lorenzo/MagicCalendar",
          "stars": 106,
          "url": "https://github.com/Vaccarini-Lorenzo/MagicCalendar",
          "primaryLanguage": "TypeScript"
        }
      ]
    }
  ]
}
