{
  "login": "westonbrown",
  "name": null,
  "avatarUrl": "https://avatars.githubusercontent.com/u/47581657?v=4",
  "htmlUrl": "https://github.com/westonbrown",
  "location": null,
  "countryCode": null,
  "generatedAt": "2026-06-04T23:40:02.570Z",
  "isPartial": true,
  "languages": [
    {
      "language": {
        "slug": "typescript",
        "name": "TypeScript",
        "githubQuery": "TypeScript"
      },
      "starsPrimary": 530,
      "repoCountPrimary": 1,
      "starsContains": 530,
      "repoCountContains": 1,
      "globalRank": null,
      "countryRank": null,
      "topRepos": [
        {
          "name": "Cyber-AutoAgent",
          "fullName": "westonbrown/Cyber-AutoAgent",
          "stars": 530,
          "url": "https://github.com/westonbrown/Cyber-AutoAgent",
          "primaryLanguage": "TypeScript"
        }
      ]
    }
  ]
}
