{
  "login": "yarin-zhang",
  "name": null,
  "avatarUrl": "https://avatars.githubusercontent.com/u/58888890?v=4",
  "htmlUrl": "https://github.com/yarin-zhang",
  "location": null,
  "countryCode": null,
  "generatedAt": "2026-06-16T15:23:30.344Z",
  "isPartial": true,
  "languages": [
    {
      "language": {
        "slug": "typescript",
        "name": "TypeScript",
        "githubQuery": "TypeScript"
      },
      "starsPrimary": 806,
      "repoCountPrimary": 1,
      "starsContains": 806,
      "repoCountContains": 1,
      "globalRank": null,
      "countryRank": null,
      "topRepos": [
        {
          "name": "AI-Gist",
          "fullName": "yarin-zhang/AI-Gist",
          "stars": 806,
          "url": "https://github.com/yarin-zhang/AI-Gist",
          "primaryLanguage": "TypeScript"
        }
      ]
    }
  ]
}
