{
  "login": "yeasin2002",
  "name": null,
  "avatarUrl": "https://avatars.githubusercontent.com/u/87494463?v=4",
  "htmlUrl": "https://github.com/yeasin2002",
  "location": null,
  "countryCode": null,
  "generatedAt": "2026-06-06T11:47:43.958Z",
  "isPartial": true,
  "languages": [
    {
      "language": {
        "slug": "typescript",
        "name": "TypeScript",
        "githubQuery": "TypeScript"
      },
      "starsPrimary": 330,
      "repoCountPrimary": 2,
      "starsContains": 330,
      "repoCountContains": 2,
      "globalRank": null,
      "countryRank": null,
      "topRepos": [
        {
          "name": "bulletproof-nextjs-starter",
          "fullName": "yeasin2002/bulletproof-nextjs-starter",
          "stars": 228,
          "url": "https://github.com/yeasin2002/bulletproof-nextjs-starter",
          "primaryLanguage": "TypeScript"
        },
        {
          "name": "react-ts-starter",
          "fullName": "yeasin2002/react-ts-starter",
          "stars": 102,
          "url": "https://github.com/yeasin2002/react-ts-starter",
          "primaryLanguage": "TypeScript"
        }
      ]
    }
  ]
}
