{
  "login": "YishaiBerg",
  "name": null,
  "avatarUrl": "https://avatars.githubusercontent.com/u/38262109?v=4",
  "htmlUrl": "https://github.com/YishaiBerg",
  "location": null,
  "countryCode": null,
  "generatedAt": "2026-05-31T23:16:10.146Z",
  "isPartial": true,
  "languages": [
    {
      "language": {
        "slug": "typescript",
        "name": "TypeScript",
        "githubQuery": "TypeScript"
      },
      "starsPrimary": 120,
      "repoCountPrimary": 1,
      "starsContains": 120,
      "repoCountContains": 1,
      "globalRank": null,
      "countryRank": null,
      "topRepos": [
        {
          "name": "vue-dynamic-marquee",
          "fullName": "YishaiBerg/vue-dynamic-marquee",
          "stars": 120,
          "url": "https://github.com/YishaiBerg/vue-dynamic-marquee",
          "primaryLanguage": "TypeScript"
        }
      ]
    }
  ]
}
