{
  "login": "Zak-JS",
  "name": null,
  "avatarUrl": "https://avatars.githubusercontent.com/u/9799548?v=4",
  "htmlUrl": "https://github.com/Zak-JS",
  "location": null,
  "countryCode": null,
  "generatedAt": "2026-06-26T23:36:28.505Z",
  "isPartial": true,
  "languages": [
    {
      "language": {
        "slug": "typescript",
        "name": "TypeScript",
        "githubQuery": "TypeScript"
      },
      "starsPrimary": 103,
      "repoCountPrimary": 1,
      "starsContains": 103,
      "repoCountContains": 1,
      "globalRank": null,
      "countryRank": null,
      "topRepos": [
        {
          "name": "expect-status",
          "fullName": "Zak-JS/expect-status",
          "stars": 103,
          "url": "https://github.com/Zak-JS/expect-status",
          "primaryLanguage": "TypeScript"
        }
      ]
    }
  ]
}
